bandcamp_extract-0.1.5.dist-info/licenses/LICENSE.md
src/__init__.py
src/extract.py
src/lib.py
bandcamp_extract-0.1.5.dist-info/METADATA
bandcamp_extract-0.1.5.dist-info/WHEEL
bandcamp_extract-0.1.5.dist-info/entry_points.txt
bandcamp_extract-0.1.5.dist-info/top_level.txt
bandcamp_extract-0.1.5.dist-info/RECORD
