Metadata-Version: 2.4
Name: bandcamp_extract
Version: 0.1.5
Summary: Extract BandCamp .zip album folders to their appropriate place
Home-page: https://github.com/JonMontgo/bandcamp_extract
Author: Jonathan Montgomery
Author-email: Jonathan Montgomery <jonathan.montgo@gmail.com>
License: MIT
Project-URL: Homepage, https://github.com/JonMontgo/bandcamp_extract
Classifier: License :: OSI Approved :: MIT License
Classifier: Programming Language :: Python :: 3
Classifier: Programming Language :: Python :: 3.6
Requires-Python: >=3.6
License-File: LICENSE.md
Requires-Dist: click==8.0.1
Requires-Dist: tinytag>=1.10.1
Dynamic: author
Dynamic: home-page
Dynamic: license-file
Dynamic: requires-python
